adafruit_hdc302x.py
adafruit_circuitpython_hdc302x-1.0.7.dist-info/licenses/LICENSE
adafruit_circuitpython_hdc302x-1.0.7.dist-info/METADATA
adafruit_circuitpython_hdc302x-1.0.7.dist-info/WHEEL
adafruit_circuitpython_hdc302x-1.0.7.dist-info/top_level.txt
adafruit_circuitpython_hdc302x-1.0.7.dist-info/RECORD
