Metadata-Version: 2.4
Name: adafruit-circuitpython-hdc302x
Version: 1.0.7
Summary: CircuitPython driver for the Adafruit HDC302x Precision Temperature/Humidity breakout
Author-email: Adafruit Industries <circuitpython@adafruit.com>
License: MIT
Project-URL: Homepage, https://github.com/adafruit/Adafruit_CircuitPython_HDC302x
Keywords: adafruit,blinka,circuitpython,micropython,hdc302x,sensor,,temperature,,humidity
Classifier: Intended Audience :: Developers
Classifier: Topic :: Software Development :: Libraries
Classifier: Topic :: Software Development :: Embedded Systems
Classifier: Topic :: System :: Hardware
Classifier: License :: OSI Approved :: MIT License
Classifier: Programming Language :: Python :: 3
License-File: LICENSE
Requires-Dist: Adafruit-Blinka
Requires-Dist: adafruit-circuitpython-busdevice
Provides-Extra: optional
Dynamic: license-file
